torch_model_manager/__init__.py
torch_model_manager/neptune_manager.py
torch_model_manager/torch_model_manager.py
utils/__init__.py
utils/helpers.py
torch_model_manager-0.2.0.dist-info/METADATA
torch_model_manager-0.2.0.dist-info/WHEEL
torch_model_manager-0.2.0.dist-info/top_level.txt
torch_model_manager-0.2.0.dist-info/RECORD
