Metadata-Version: 2.1
Name: torch-model-manager
Version: 0.2.0
Summary: A package for managing PyTorch models
Home-page: https://github.com/Billal-MOKHTARI/torch-model-manager
Author: Billal MOKHTARI
Author-email: mokhtaribillal1@gmail.com
Keywords: PyTorch,Deep Learning,Machine Learning,High Level Programming
Classifier: License :: OSI Approved :: MIT License
Classifier: Programming Language :: Python :: 3
Classifier: Operating System :: OS Independent
Requires-Dist: torch
Requires-Dist: numpy
Requires-Dist: torchvision
Requires-Dist: torchcam
Requires-Dist: neptune
